{
    "fluentMethods": true,
    "relationships": [
        {
            "relationshipType": "one-to-one",
            "relationshipName": "addressInfo",
            "otherEntityName": "addressInfo",
            "otherEntityField": "id",
            "ownerSide": true,
            "otherEntityRelationshipName": "party"
        }
    ],
    "fields": [
        {
            "fieldName": "partyIdValue",
            "fieldType": "String"
        },
        {
            "fieldName": "partyIdType",
            "fieldType": "PartyIdType",
            "fieldValues": "RMID,TPSSID,MDID"
        },
        {
            "fieldName": "partyType",
            "fieldType": "PartyType",
            "fieldValues": "INDIVIDUAL,ORGANIZATION"
        }
    ],
    "changelogDate": "20170703200049",
    "entityTableName": "party",
    "dto": "no",
    "pagination": "no",
    "service": "no"
}